LICENSE.txt
MANIFEST.in
README.md
pyproject.toml
setup.py
src/Bext.egg-info/PKG-INFO
src/Bext.egg-info/SOURCES.txt
src/Bext.egg-info/dependency_links.txt
src/Bext.egg-info/requires.txt
src/Bext.egg-info/top_level.txt
src/bext/__init__.py
tests/test_bext.py