Metadata-Version: 2.1
Name: Bext
Version: 0.1.0
Summary: A cross-platform Python 2/3 module for colorful, boring, text-based terminal programs.
Home-page: https://github.com/asweigart/bext
Author: Al Sweigart
Author-email: al@inventwithpython.com
Classifier: Programming Language :: Python
Classifier: Programming Language :: Python :: 2
Classifier: Programming Language :: Python :: 3
License-File: LICENSE.txt
